MANIFEST.in
README.md
setup.py
pixplot/__init__.py
pixplot/pixplot.py
pixplot.egg-info/PKG-INFO
pixplot.egg-info/SOURCES.txt
pixplot.egg-info/dependency_links.txt
pixplot.egg-info/entry_points.txt
pixplot.egg-info/requires.txt
pixplot.egg-info/top_level.txt
pixplot/web/favicon.ico
pixplot/web/index.html
pixplot/web/assets/css/no-ui-slider.css
pixplot/web/assets/css/style.css
pixplot/web/assets/images/date-layout.png
pixplot/web/assets/images/dhlab-logo.svg
pixplot/web/assets/images/heightmap.jpg
pixplot/web/assets/images/preview.png
pixplot/web/assets/images/icons/az-layout.svg
pixplot/web/assets/images/icons/caret-icon.png
pixplot/web/assets/images/icons/categorical-layout.svg
pixplot/web/assets/images/icons/chevron.png
pixplot/web/assets/images/icons/custom-layout.svg
pixplot/web/assets/images/icons/date-layout.svg
pixplot/web/assets/images/icons/download-icon.png
pixplot/web/assets/images/icons/eye-icon.png
pixplot/web/assets/images/icons/gear-icon.svg
pixplot/web/assets/images/icons/geographic-layout.svg
pixplot/web/assets/images/icons/grid-layout.svg
pixplot/web/assets/images/icons/lasso.png
pixplot/web/assets/images/icons/pan.svg
pixplot/web/assets/images/icons/pinch-icon.svg
pixplot/web/assets/images/icons/pose-icon.svg
pixplot/web/assets/images/icons/pose-layout.svg
pixplot/web/assets/images/icons/refresh.svg
pixplot/web/assets/images/icons/save.svg
pixplot/web/assets/images/icons/scatter-layout.svg
pixplot/web/assets/images/icons/search-icon.svg
pixplot/web/assets/images/icons/select.svg
pixplot/web/assets/js/object-assign-polyfill.js
pixplot/web/assets/js/tsne.js
pixplot/web/assets/json/flat-continents.json
pixplot/web/assets/vendor/dist/d3.min.js
pixplot/web/assets/vendor/dist/gsap.min.js
pixplot/web/assets/vendor/dist/gunzip.min.js
pixplot/web/assets/vendor/dist/jszip.min.js
pixplot/web/assets/vendor/dist/lodash.min.js
pixplot/web/assets/vendor/dist/no-ui-slider.min.js
pixplot/web/assets/vendor/dist/papaparse.min.js
pixplot/web/assets/vendor/dist/stats.min.js
pixplot/web/assets/vendor/dist/three.min.js
pixplot/web/assets/vendor/dist/trackball-controls.min.js
pixplot/web/assets/vendor/src/jszip.js
pixplot/web/assets/vendor/src/stats.js
