Metadata-Version: 1.0
Name: pixplot
Version: 0.0.112
Summary: Visualize large image collections with WebGL
Home-page: https://github.com/yaledhlab/pix-plot
Author: Douglas Duhaime
Author-email: douglas.duhaime@gmail.com
License: MIT
Keywords: computer-vision,webgl,three.js,tensorflow,machine-learning
Platform: UNKNOWN
